{
  "fitnessActivity": "walking",
  "startTime": "2025-07-15T19:35:52.551Z",
  "endTime": "2025-07-15T22:10:27.625Z",
  "duration": "6046.926s",
  "segment": [{
    "fitnessActivity": "walking",
    "startTime": "2025-07-15T19:35:52.551Z",
    "endTime": "2025-07-15T20:07:10.468Z"
  }, {
    "fitnessActivity": "walking",
    "startTime": "2025-07-15T20:08:50.269Z",
    "endTime": "2025-07-15T20:21:23.264Z"
  }, {
    "fitnessActivity": "walking",
    "startTime": "2025-07-15T20:21:23.264Z",
    "endTime": "2025-07-15T20:21:39.353Z"
  }, {
    "fitnessActivity": "walking",
    "startTime": "2025-07-15T20:22:40.233Z",
    "endTime": "2025-07-15T20:26:10.262Z"
  }, {
    "fitnessActivity": "walking",
    "startTime": "2025-07-15T20:26:10.262Z",
    "endTime": "2025-07-15T20:30:47.422Z"
  }, {
    "fitnessActivity": "walking",
    "startTime": "2025-07-15T20:41:21.577Z",
    "endTime": "2025-07-15T20:42:40.260Z"
  }, {
    "fitnessActivity": "walking",
    "startTime": "2025-07-15T20:55:29.403Z",
    "endTime": "2025-07-15T20:56:45.279Z"
  }, {
    "fitnessActivity": "walking",
    "startTime": "2025-07-15T21:01:46.210Z",
    "endTime": "2025-07-15T21:04:07.278Z"
  }, {
    "fitnessActivity": "walking",
    "startTime": "2025-07-15T21:05:32.135Z",
    "endTime": "2025-07-15T21:06:53.258Z"
  }, {
    "fitnessActivity": "walking",
    "startTime": "2025-07-15T21:19:05.988Z",
    "endTime": "2025-07-15T21:19:07.665Z"
  }, {
    "fitnessActivity": "walking",
    "startTime": "2025-07-15T21:19:07.665Z",
    "endTime": "2025-07-15T21:25:47.203Z"
  }, {
    "fitnessActivity": "walking",
    "startTime": "2025-07-15T21:29:33.241Z",
    "endTime": "2025-07-15T21:38:45.267Z"
  }, {
    "fitnessActivity": "walking",
    "startTime": "2025-07-15T21:39:05.468Z",
    "endTime": "2025-07-15T21:39:16.042Z"
  }, {
    "fitnessActivity": "walking",
    "startTime": "2025-07-15T21:39:16.042Z",
    "endTime": "2025-07-15T21:41:16.134Z"
  }, {
    "fitnessActivity": "walking",
    "startTime": "2025-07-15T21:42:29.942Z",
    "endTime": "2025-07-15T21:42:32.239Z"
  }, {
    "fitnessActivity": "walking",
    "startTime": "2025-07-15T21:42:32.239Z",
    "endTime": "2025-07-15T21:55:31.012Z"
  }, {
    "fitnessActivity": "walking",
    "startTime": "2025-07-15T21:56:38.132Z",
    "endTime": "2025-07-15T21:57:08.480Z"
  }, {
    "fitnessActivity": "walking",
    "startTime": "2025-07-15T21:57:08.480Z",
    "endTime": "2025-07-15T22:00:57.280Z"
  }, {
    "fitnessActivity": "walking",
    "startTime": "2025-07-15T22:03:35.764Z",
    "endTime": "2025-07-15T22:03:39.239Z"
  }, {
    "fitnessActivity": "walking",
    "startTime": "2025-07-15T22:03:39.239Z",
    "endTime": "2025-07-15T22:10:27.625Z"
  }],
  "aggregate": [{
    "metricName": "com.google.heart_minutes.summary",
    "floatValue": 5.0
  }, {
    "metricName": "com.google.calories.expended",
    "floatValue": 429.9210639302024
  }, {
    "metricName": "com.google.step_count.delta",
    "intValue": 8450
  }, {
    "metricName": "com.google.distance.delta",
    "floatValue": 4810.57151437111
  }, {
    "metricName": "com.google.speed.summary",
    "floatValue": 0.6636973510333808
  }, {
    "metricName": "com.google.active_minutes",
    "intValue": 105
  }]
}