{
  "fitnessActivity": "walking",
  "startTime": "2026-05-01T20:08:16.729Z",
  "endTime": "2026-05-01T20:19:40.914Z",
  "duration": "684.185s",
  "segment": [{
    "fitnessActivity": "walking",
    "startTime": "2026-05-01T20:08:16.729Z",
    "endTime": "2026-05-01T20:10:29.606Z"
  }, {
    "fitnessActivity": "walking",
    "startTime": "2026-05-01T20:10:29.606Z",
    "endTime": "2026-05-01T20:19:40.914Z"
  }],
  "aggregate": [{
    "metricName": "com.google.heart_minutes.summary",
    "floatValue": 2.0
  }, {
    "metricName": "com.google.calories.expended",
    "floatValue": 44.7760637439168
  }, {
    "metricName": "com.google.step_count.delta",
    "intValue": 874
  }, {
    "metricName": "com.google.distance.delta",
    "floatValue": 498.0025731893644
  }, {
    "metricName": "com.google.speed.summary",
    "floatValue": 0.8869950549167293
  }, {
    "metricName": "com.google.active_minutes",
    "intValue": 11
  }]
}